{
    "platform": "naurok",
    "utl": "https://naurok.com.ua/test/periodichniy-zakon-d-i-mendeleeva-periodichno-sistemi-himichnih-elementiv-struktura-3057403.html",
    "name_test": "Періодичний закон Д.І. Менделєєва. Періодична система хімічних елементів, її структура",
    "object": "Хімія",
    "klass": "8 клас",
    "questions": "12",
    "answers": [
        {
            "type": "quiz",
            "text": "Укажіть характеристику, яка лежить в основі сучасного формулювання періодичного закону.",
            "img": null,
            "value": [
                {
                    "text": "належність елементів до металів чи неметалів",
                    "img": null
                },
                {
                    "text": "заряд ядра атома",
                    "img": null
                },
                {
                    "text": "атомна маса елемента",
                    "img": null
                },
                {
                    "text": "валентність елемента",
                    "img": null
                }
            ]
        },
        {
            "type": "quiz",
            "text": "Проаналізуйте твердження. Чи є з-поміж них правильні?І.Короткийідовгийваріантиперіодичноїсистемимістятьоднакову кількість груп.ІІ. У структурі короткого і довгого варіантів періодичної системи є по сім періодів.",
            "img": null,
            "value": [
                {
                    "text": "правильне лише твердження І",
                    "img": null
                },
                {
                    "text": "правильне лише твердження ІІ",
                    "img": null
                },
                {
                    "text": "правильні обидва твердження",
                    "img": null
                },
                {
                    "text": "неправильні обидва твердження",
                    "img": null
                }
            ]
        },
        {
            "type": "quiz",
            "text": "Укажіть елемент, розташований у головній підгрупі періодичної системи.",
            "img": null,
            "value": [
                {
                    "text": "Ферум",
                    "img": null
                },
                {
                    "text": "Купрум",
                    "img": null
                },
                {
                    "text": "Кальцій",
                    "img": null
                },
                {
                    "text": "Меркурій",
                    "img": null
                }
            ]
        },
        {
            "type": "quiz",
            "text": "Укажіть елемент, розташований у побічній підгрупі періодичної системи.",
            "img": null,
            "value": [
                {
                    "text": "Магній",
                    "img": null
                },
                {
                    "text": "Купрум",
                    "img": null
                },
                {
                    "text": "Кальцій",
                    "img": null
                },
                {
                    "text": "Хлор",
                    "img": null
                }
            ]
        },
        {
            "type": "quiz",
            "text": "Укажіть, як змінюється металічний характер властивостей елементів у ряду Mg – Ca – Sr – Ba.",
            "img": null,
            "value": [
                {
                    "text": "послаблюється",
                    "img": null
                },
                {
                    "text": "не змінюється",
                    "img": null
                },
                {
                    "text": "посилюється",
                    "img": null
                },
                {
                    "text": "спочатку послаблюється, а далі посилюється",
                    "img": null
                }
            ]
        },
        {
            "type": "quiz",
            "text": "Укажіть, як змінюється неметалічний характер властивостей елементів у ряду I – Br – Cl – F.",
            "img": null,
            "value": [
                {
                    "text": "послаблюється",
                    "img": null
                },
                {
                    "text": "не змінюється",
                    "img": null
                },
                {
                    "text": "посилюється",
                    "img": null
                },
                {
                    "text": "спочатку послаблюється, а далі посилюється",
                    "img": null
                }
            ]
        },
        {
            "type": "quiz",
            "text": "Укажіть елемент, який утворює летку сполуку з Гідрогеном типу HR.",
            "img": null,
            "value": [
                {
                    "text": "О",
                    "img": null
                },
                {
                    "text": "Mn",
                    "img": null
                },
                {
                    "text": "Cl",
                    "img": null
                },
                {
                    "text": "Ca",
                    "img": null
                }
            ]
        },
        {
            "type": "quiz",
            "text": "Укажіть загальну формулу вищого оксиду лужних елементів.",
            "img": null,
            "value": [
                {
                    "text": "RO",
                    "img": null
                },
                {
                    "text": "R2O",
                    "img": null
                },
                {
                    "text": "R2O3",
                    "img": null
                },
                {
                    "text": "R2O7",
                    "img": null
                }
            ]
        },
        {
            "type": "quiz",
            "text": "Укажіть хімічний елемент, розташований у IV-A групі 3-го періоду.",
            "img": null,
            "value": [
                {
                    "text": "Sc",
                    "img": null
                },
                {
                    "text": "Ga",
                    "img": null
                },
                {
                    "text": "Si",
                    "img": null
                },
                {
                    "text": "C",
                    "img": null
                }
            ]
        },
        {
            "type": "quiz",
            "text": "Укажіть пару елементів з однаковою кількістю енергетичних рівнів.",
            "img": null,
            "value": [
                {
                    "text": "Mg, Ca",
                    "img": null
                },
                {
                    "text": "Mg, Al",
                    "img": null
                },
                {
                    "text": "K, C",
                    "img": null
                },
                {
                    "text": "K, Mg",
                    "img": null
                }
            ]
        },
        {
            "type": "quiz",
            "text": "Укажіть заряд ядра атома Натрію.",
            "img": null,
            "value": [
                {
                    "text": "+11",
                    "img": null
                },
                {
                    "text": "-11",
                    "img": null
                },
                {
                    "text": "+23",
                    "img": null
                },
                {
                    "text": "-23",
                    "img": null
                }
            ]
        },
        {
            "type": "quiz",
            "text": "Укажіть число електронів в атомі елемента з нуклонним числом 14.",
            "img": null,
            "value": [
                {
                    "text": "3",
                    "img": null
                },
                {
                    "text": "14",
                    "img": null
                },
                {
                    "text": "7",
                    "img": null
                },
                {
                    "text": "5",
                    "img": null
                }
            ]
        }
    ]
}